LICENSE
README.md
setup.py
coingecko_python.egg-info/PKG-INFO
coingecko_python.egg-info/SOURCES.txt
coingecko_python.egg-info/dependency_links.txt
coingecko_python.egg-info/not-zip-safe
coingecko_python.egg-info/requires.txt
coingecko_python.egg-info/top_level.txt
python/prod/__init__.py
python/prod/explorer/__init__.py
python/prod/explorer/coingecko.py