Metadata-Version: 2.1
Name: coingecko-python
Version: 0.0.1
Summary: Python API for coingecko
Home-page: https://github.com/defipy-devs
Author: icmoore
Author-email: defipy.devs@gmail.com
License: MIT
License-File: LICENSE
Requires-Dist: requests
